{
  "module": "sessions",
  "operations": [
    {
      "operationId": "createSession",
      "action": "agents:CreateSession",
      "description": "Create a new session for an agent"
    },
    {
      "operationId": "listSessions",
      "action": "agents:ListSessions",
      "description": "List sessions"
    },
    {
      "operationId": "getSession",
      "action": "agents:GetSession",
      "description": "Get a session"
    },
    {
      "operationId": "updateSession",
      "action": "agents:UpdateSession",
      "description": "Update session name, status, or tags"
    },
    {
      "operationId": "deleteSession",
      "action": "agents:DeleteSession",
      "description": "Delete a session"
    },
    {
      "operationId": "addSessionMessage",
      "action": "agents:SendSessionMessage",
      "description": "Save a user message or trigger generation"
    },
    {
      "operationId": "generateSessionResponse",
      "action": "agents:SendSessionMessage",
      "description": "Generate an assistant response in a session"
    },
    {
      "operationId": "submitSessionToolOutputs",
      "action": "agents:SubmitSessionToolOutputs",
      "description": "Submit tool outputs for client tools in a session"
    }
  ]
}
